{
  "date": "2025-05-03",
  "districts": {
    "PALGHAR": 5.5,
    "THANE": 25.8,
    "MUMBAI": 5.5,
    "RAIGAD": 45.2,
    "RATNAGIRI": null,
    "SINDHUDURG": null,
    "DHULE": 25.8,
    "NANDURBAR": 67.8,
    "JALGAON": null,
    "NASHIK": 12.3,
    "AHMEDNAGAR": null,
    "PUNE": 25.8,
    "KOLHAPUR": 25.8,
    "SATARA": 5.5,
    "SOUTH SATARA": 45.2,
    "SANGLI": null,
    "SOLAPUR": 5.5,
    "CHHATRAPATI SAMBHAJINAGAR": 5.5,
    "JALNA": 12.3,
    "PARBHANI": 5.5,
    "BEED": 25.8,
    "HINGOLI": null,
    "NANDED": null,
    "LATUR": 12.3,
    "DHARASHIV": null
  }
}