{
  "date": "2025-06-15",
  "leadDay": "D1",
  "districts": {
    "PALGHAR": 8,
    "THANE": 10,
    "MUMBAI": null,
    "RAIGAD": null,
    "RATNAGIRI": 5,
    "SINDHUDURG": null,
    "DHULE": 5,
    "NANDURBAR": null,
    "JALGAON": 10,
    "NASHIK": null,
    "AHMEDNAGAR": null,
    "PUNE": 7,
    "KOLHAPUR": null,
    "SATARA": null,
    "SOUTH SATARA": null,
    "SANGLI": 7,
    "SOLAPUR": null,
    "CHHATRAPATI SAMBHAJINAGAR": null,
    "JALNA": 7,
    "PARBHANI": null,
    "BEED": null,
    "HINGOLI": null,
    "NANDED": null,
    "LATUR": null,
    "DHARASHIV": 5,
    "NAGPUR": null
  }
}